Metadata-Version: 2.1
Name: novusspace
Version: 0.4.2
Summary: Module for novus space software
Home-page: https://novusspace.inovaperf.me
Author: novus-alex
Author-email: alexandre@hachet.com
License: MIT
Download-URL: https://github.com/novus-alex/novus-module/archive/0.1.tar.gz
Keywords: NOVUS,SPACE,PROJECT
Platform: UNKNOWN
Classifier: Development Status :: 3 - Alpha
Classifier: Intended Audience :: Developers
Classifier: Topic :: Software Development :: Build Tools
Classifier: License :: OSI Approved :: MIT License
Classifier: Programming Language :: Python :: 3.1
Classifier: Programming Language :: Python :: 3.8
